adwrapper/__init__.py
adwrapper-0.0.5.dist-info/DESCRIPTION.rst
adwrapper-0.0.5.dist-info/METADATA
adwrapper-0.0.5.dist-info/RECORD
adwrapper-0.0.5.dist-info/WHEEL
adwrapper-0.0.5.dist-info/metadata.json
adwrapper-0.0.5.dist-info/top_level.txt
