Metadata-Version: 2.0
Name: adwrapper
Version: 0.0.5
Summary: Simple wrapper for common Active Directory actions.
Home-page: https://github.com/incognitjoe/adwrapper
Author: Joe Butler
Author-email: incognitjoeb@gmail.com
License: UNKNOWN
Platform: UNKNOWN
Requires-Dist: python-ldap
